[
  {
    "title": "% AVANCE DEL PLAN DE TRABAJO",
    "value": "0.877",
    "col1": "0.18",
    "col2": "0.2",
    "col3": "0.22",
    "col4": "0.24",
    "editable": "1",
    "is_total": "0"
  },
  {
    "title": "% AVANCE SEMANAL",
    "value": "0.79500000000000004",
    "col1": "0.18",
    "col2": "2.0000000000000018E-2",
    "col3": "1.999999999999999E-2",
    "col4": "1.999999999999999E-2",
    "editable": "0",
    "is_total": "0"
  },
  {
    "title": "ESFUERZO EN HORAS ESPERADO",
    "value": "5137.2000000000016",
    "col1": "1075.1400000000001",
    "col2": "119.46000000000009",
    "col3": "119.45999999999995",
    "col4": "119.45999999999995",
    "editable": "0",
    "is_total": "0"
  },
  {
    "title": "HC ESPERADO",
    "value": "",
    "col1": "1075.1400000000001",
    "col2": "7.4662500000000058",
    "col3": "2.9864999999999986",
    "col4": "2.9864999999999986",
    "editable": "0",
    "is_total": "0"
  },
  {
    "title": "INGRESO",
    "value": "3049411.551",
    "col1": "508177.8",
    "col2": "56464.200000000048",
    "col3": "56464.199999999975",
    "col4": "56464.199999999975",
    "editable": "0",
    "is_total": "0"
  },
  {
    "title": "COSTO",
    "value": "1616030.394839348",
    "col1": "256713.86789058306",
    "col2": "11879.616987999287",
    "col3": "29323.072512280465",
    "col4": "32116.821650300564",
    "editable": "0",
    "is_total": "0"
  },
  {
    "title": "RENTABILIDAD",
    "value": "1433381.1561606519",
    "col1": "251463.93210941693",
    "col2": "44584.583012000759",
    "col3": "27141.12748771951",
    "col4": "24347.378349699411",
    "editable": "0",
    "is_total": "0"
  },
  {
    "title": "MARGEN",
    "value": "0.47005172381228771",
    "col1": "0.49483454828096962",
    "col2": "0.78960798190713266",
    "col3": "0.4806785093514036",
    "col4": "0.43120027113993331",
    "editable": "0",
    "is_total": "0"
  },
  {
    "title": "POR SEMANA INGRESOS",
    "value": "3049412",
    "col1": "0",
    "col2": "0",
    "col3": "0",
    "col4": "0",
    "editable": "0",
    "is_total": "1"
  }]
